{"cameraMode":{"drawMode":0,"name":"Shaded","section":"Shading Mode"},"sceneLighting":true,"audioPlay":false,"sceneViewState":{"showFog":true,"showMaterialUpdate":false,"showSkybox":true,"showFlares":true,"showImageEffects":true,"showParticleSystems":true},"in2DMode":false,"pivot":{"x":2.784653663635254,"y":23.504291534423829,"z":153.91485595703126},"rotation":{"x":0.07927364110946655,"y":0.10652149468660355,"z":-0.008527352474629879,"w":0.9911950826644898},"size":318.9211120605469,"orthographic":false}